lxa5-crab/__init__.py
lxa5-crab/crab_nebula.py
lxa5crab/__init__.py
lxa5crab/crab_nebula.py
lxa5crab/laplacian.py
lxa5crab-0.6.dist-info/DESCRIPTION.rst
lxa5crab-0.6.dist-info/METADATA
lxa5crab-0.6.dist-info/RECORD
lxa5crab-0.6.dist-info/WHEEL
lxa5crab-0.6.dist-info/metadata.json
lxa5crab-0.6.dist-info/top_level.txt
