Metadata-Version: 2.0
Name: lxa5crab
Version: 0.6
Summary: Linguistica - Crab Nebula, py 2+3 standalone implementation.
Home-page: UNKNOWN
Author: UNKNOWN
Author-email: UNKNOWN
License: GPLv3
Keywords: unsupervised learningmorphological analysis,linguistica
Platform: UNKNOWN
